density/__init__.py
density/validatedensitydict.py
density-1.0.0.dist-info/LICENSE
density-1.0.0.dist-info/METADATA
density-1.0.0.dist-info/WHEEL
density-1.0.0.dist-info/entry_points.txt
density-1.0.0.dist-info/top_level.txt
density-1.0.0.dist-info/RECORD
