Metadata-Version: 2.2
Name: density
Version: 1.0.0
Summary: Specifications of parametric density functions
Home-page: https://github.com/microprediction/density
Author: microprediction
Author-email: peter.cotton@microprediction.com
License: MIT
Classifier: License :: OSI Approved :: MIT License
Classifier: Programming Language :: Python :: 3
Classifier: Programming Language :: Python :: 3.12
License-File: LICENSE
Requires-Dist: pydantic
Dynamic: author
Dynamic: author-email
Dynamic: classifier
Dynamic: description
Dynamic: description-content-type
Dynamic: home-page
Dynamic: license
Dynamic: requires-dist
Dynamic: summary
